{
  "task": {
    "name": "Carbonation equilibrium - MIX_4100",
    "description": "Fly ash + cement + sodium silicate + coal gangue system",
    "calculation_type": "equilibrium",
    "database": "Cemdata18",
    "database_version": "18.1"
  },
  "conditions": {
    "temperature_K": 298.15,
    "pressure_bar": 1.01325,
    "pCO2_bar": 0.303975
  },
  "mix_parameters": {
    "R_binder_aggregate": 1.2,
    "f_FA_replacement": 0.3,
    "yCO2_volume_fraction": 0.3,
    "w_SS_dosage": 0.03,
    "w_b_ratio": 1.1
  },
  "system": {
    "components": [
      "Ca",
      "Si",
      "Al",
      "Fe",
      "Mg",
      "K",
      "Na",
      "S",
      "O",
      "H",
      "C"
    ],
    "component_amounts": {
      "Ca": 0.9482711,
      "Si": 1.77725513,
      "Al": 0.57396333,
      "Fe": 0.0843058,
      "Mg": 0.01299033,
      "K": 0.03691849,
      "Na": 0.10257964,
      "S": 0.07854974,
      "O": 13.63783185,
      "H": 15.59747029,
      "C": 0.02197059
    },
    "component_units": "moles"
  },
  "phases": {
    "enabled": [
      "C3S",
      "C2S",
      "C3A",
      "C4AF",
      "Gypsum",
      "Anhydrite",
      "Portlandite",
      "CSHQ_TobH",
      "Ettringite",
      "Monosulfoaluminate",
      "Hydrotalcite",
      "Hydrogarnet",
      "NASH_gel",
      "CNASH_gel",
      "Calcite",
      "Aragonite",
      "Vaterite",
      "Monocarboaluminate",
      "SiO2am",
      "Quartz",
      "Kaolinite",
      "Illite",
      "Montmorillonite",
      "Mullite",
      "Magnetite",
      "Hematite"
    ],
    "aqueous_solution": {
      "enabled": true,
      "name": "AqueousSolution"
    },
    "gas_phase": {
      "enabled": true,
      "composition": {
        "CO2": 0.303975,
        "H2O_gas": 0.709275
      },
      "units": "bar"
    }
  },
  "solver": {
    "method": "IPM",
    "max_iterations": 500,
    "tolerance": 1e-06,
    "timeout_seconds": 300
  },
  "output": {
    "phases": true,
    "phase_amounts": true,
    "aqueous_species": true,
    "element_distribution": true,
    "format": "json"
  }
}