{
  "converged": true,
  "method": "simplified_thermodynamic_model",
  "note": "Using simplified model until Cemdata18 integration complete",
  "temperature_K": 298.15,
  "pressure_bar": 1.01325,
  "CO2_fraction": 0.2,
  "pCO2_bar": 0.20265,
  "phases": {
    "Calcite": {
      "moles": 0.00403009548375,
      "mass_kg": 0.0004033722569685375
    },
    "C-S-H_1.0": {
      "moles": 0.21432881451625,
      "mass_kg": 0.036435898467762504
    },
    "Silica_gel": {
      "moles": 0.9165933554837501,
      "mass_kg": 0.05506892879746371
    },
    "Ettringite": {
      "moles": 0.0068346,
      "mass_kg": 0.008577422999999999
    },
    "Hydrotalcite": {
      "moles": 0.019300623,
      "mass_kg": 0.008550175989
    }
  },
  "pH": 9.48675,
  "pe": 4.0,
  "Eh": 0.24,
  "system_mass_kg": 0.10903579851119474,
  "input_composition": {
    "Ca": 0.21835891,
    "Si": 1.13092217,
    "Al": 0.47250869,
    "Fe": 0.06167519,
    "Mg": 0.06433541,
    "K": 0.06043569,
    "Na": 0.07459528,
    "S": 0.0410076,
    "O": 6.88276847,
    "H": 6.66101226,
    "C": 0.00795479
  },
  "execution_time": 9.5367431640625e-06,
  "mix_id": "MIX_0267",
  "input_file": "/teamspace/studios/this_studio/inputs/generated/MIX_0267.inp"
}