{
  "converged": true,
  "method": "simplified_thermodynamic_model",
  "note": "Using simplified model until Cemdata18 integration complete",
  "temperature_K": 298.15,
  "pressure_bar": 1.01325,
  "CO2_fraction": 0.4,
  "pCO2_bar": 0.4053,
  "phases": {
    "Calcite": {
      "moles": 0.01449239,
      "mass_kg": 0.0014505433151
    },
    "C-S-H_1.0": {
      "moles": 0.10125834,
      "mass_kg": 0.017213917800000002
    },
    "Silica_gel": {
      "moles": 1.14999812,
      "mass_kg": 0.06909188704960001
    },
    "Ettringite": {
      "moles": 0.000854325,
      "mass_kg": 0.0010721778749999999
    },
    "Hydrotalcite": {
      "moles": 0.011797719,
      "mass_kg": 0.005226389517
    }
  },
  "pH": 8.5,
  "pe": 4.0,
  "Eh": 0.24,
  "system_mass_kg": 0.09405491555670001,
  "input_composition": {
    "Ca": 0.11575073,
    "Si": 1.25125646,
    "Al": 0.47716339,
    "Fe": 0.08203236,
    "Mg": 0.03932573,
    "K": 0.06685634,
    "Na": 0.08529898,
    "S": 0.00512595,
    "O": 5.94817757,
    "H": 4.66270854,
    "C": 0.01449239
  },
  "execution_time": 1.0967254638671875e-05,
  "mix_id": "MIX_1117",
  "input_file": "/teamspace/studios/this_studio/inputs/generated/MIX_1117.inp"
}