{
  "converged": true,
  "method": "simplified_thermodynamic_model",
  "note": "Using simplified model until Cemdata18 integration complete",
  "temperature_K": 298.15,
  "pressure_bar": 1.01325,
  "CO2_fraction": 0.3,
  "pCO2_bar": 0.303975,
  "phases": {
    "Calcite": {
      "moles": 0.015081035681249999,
      "mass_kg": 0.0015094608613363124
    },
    "C-S-H_1.0": {
      "moles": 0.7208125643187501,
      "mass_kg": 0.12253813593418753
    },
    "Silica_gel": {
      "moles": 0.6001426056812499,
      "mass_kg": 0.03605656774932949
    },
    "Ettringite": {
      "moles": 0.02562975166666667,
      "mass_kg": 0.03216533834166667
    },
    "Hydrotalcite": {
      "moles": 0.049446213,
      "mass_kg": 0.021904672359
    }
  },
  "pH": 8.980125000000001,
  "pe": 4.0,
  "Eh": 0.24,
  "system_mass_kg": 0.21417417524552,
  "input_composition": {
    "Ca": 0.7358936,
    "Si": 1.32095517,
    "Al": 0.60617116,
    "Fe": 0.05961618,
    "Mg": 0.16482071,
    "K": 0.05860121,
    "Na": 0.12406373,
    "S": 0.15377851,
    "O": 12.12772674,
    "H": 13.98812569,
    "C": 0.0198451
  },
  "execution_time": 1.8835067749023438e-05,
  "mix_id": "MIX_2537",
  "input_file": "/teamspace/studios/this_studio/inputs/generated/MIX_2537.inp"
}