{
  "converged": true,
  "method": "simplified_thermodynamic_model",
  "note": "Using simplified model until Cemdata18 integration complete",
  "temperature_K": 298.15,
  "pressure_bar": 1.01325,
  "CO2_fraction": 0.35,
  "pCO2_bar": 0.3546375,
  "phases": {
    "Calcite": {
      "moles": 0.011685545005312499,
      "mass_kg": 0.001169606199581728
    },
    "C-S-H_1.0": {
      "moles": 0.13338180499468752,
      "mass_kg": 0.02267490684909688
    },
    "Silica_gel": {
      "moles": 1.0682814850053124,
      "mass_kg": 0.06418235161911917
    },
    "Ettringite": {
      "moles": 0.002562975,
      "mass_kg": 0.0032165336249999994
    },
    "Hydrotalcite": {
      "moles": 0.013941405,
      "mass_kg": 0.006176042415
    }
  },
  "pH": 8.7268125,
  "pe": 4.0,
  "Eh": 0.24,
  "system_mass_kg": 0.09741944070779777,
  "input_composition": {
    "Ca": 0.14506735,
    "Si": 1.20166329,
    "Al": 0.47583348,
    "Fe": 0.07621603,
    "Mg": 0.04647135,
    "K": 0.06502187,
    "Na": 0.05274692,
    "S": 0.01537785,
    "O": 6.38524825,
    "H": 5.6618604,
    "C": 0.01318027
  },
  "execution_time": 8.821487426757812e-06,
  "mix_id": "MIX_0870",
  "input_file": "/teamspace/studios/this_studio/inputs/generated/MIX_0870.inp"
}