{
  "converged": true,
  "method": "simplified_thermodynamic_model",
  "note": "Using simplified model until Cemdata18 integration complete",
  "temperature_K": 298.15,
  "pressure_bar": 1.01325,
  "CO2_fraction": 0.25,
  "pCO2_bar": 0.2533125,
  "phases": {
    "Calcite": {
      "moles": 0.0086300972296875,
      "mass_kg": 0.0008637864317194218
    },
    "C-S-H_1.0": {
      "moles": 0.24862148277031249,
      "mass_kg": 0.042265652070953126
    },
    "Silica_gel": {
      "moles": 1.2114954372296873,
      "mass_kg": 0.07278664586875962
    },
    "Ettringite": {
      "moles": 0.0034173,
      "mass_kg": 0.0042887114999999995
    },
    "Hydrotalcite": {
      "moles": 0.01829577,
      "mass_kg": 0.00810502611
    }
  },
  "pH": 9.2334375,
  "pe": 4.0,
  "Eh": 0.24,
  "system_mass_kg": 0.12830982198143218,
  "input_composition": {
    "Ca": 0.25725158,
    "Si": 1.46011692,
    "Al": 0.5493143,
    "Fe": 0.10426819,
    "Mg": 0.0609859,
    "K": 0.073277,
    "Na": 0.07635189,
    "S": 0.0205038,
    "O": 10.04428646,
    "H": 11.32372072,
    "C": 0.01362759
  },
  "execution_time": 5.555152893066406e-05,
  "mix_id": "MIX_2182",
  "input_file": "/teamspace/studios/this_studio/inputs/generated/MIX_2182.inp"
}