{
  "converged": true,
  "method": "simplified_thermodynamic_model",
  "note": "Using simplified model until Cemdata18 integration complete",
  "temperature_K": 298.15,
  "pressure_bar": 1.01325,
  "CO2_fraction": 0.25,
  "pCO2_bar": 0.2533125,
  "phases": {
    "Calcite": {
      "moles": 0.015340725323437497,
      "mass_kg": 0.001535453197622859
    },
    "C-S-H_1.0": {
      "moles": 0.7887621746765625,
      "mass_kg": 0.13408956969501565
    },
    "Silica_gel": {
      "moles": 0.8813492153234375,
      "mass_kg": 0.052951460856632125
    },
    "Ettringite": {
      "moles": 0.023921101666666666,
      "mass_kg": 0.030020982591666665
    },
    "Hydrotalcite": {
      "moles": 0.050585049,
      "mass_kg": 0.022409176707
    }
  },
  "pH": 9.2334375,
  "pe": 4.0,
  "Eh": 0.24,
  "system_mass_kg": 0.24100664304793729,
  "input_composition": {
    "Ca": 0.8041029,
    "Si": 1.67011139,
    "Al": 0.68164686,
    "Fe": 0.09639285,
    "Mg": 0.16861683,
    "K": 0.06960805,
    "Na": 0.22812517,
    "S": 0.14352661,
    "O": 19.4299213,
    "H": 26.64404881,
    "C": 0.02422419
  },
  "execution_time": 1.0013580322265625e-05,
  "mix_id": "MIX_4095",
  "input_file": "/teamspace/studios/this_studio/inputs/generated/MIX_4095.inp"
}