{
  "converged": true,
  "method": "simplified_thermodynamic_model",
  "note": "Using simplified model until Cemdata18 integration complete",
  "temperature_K": 298.15,
  "pressure_bar": 1.01325,
  "CO2_fraction": 0.15,
  "pCO2_bar": 0.1519875,
  "phases": {
    "Calcite": {
      "moles": 0.0037245638784374996,
      "mass_kg": 0.0003727915985928093
    },
    "C-S-H_1.0": {
      "moles": 0.3363946261215625,
      "mass_kg": 0.057187086440665634
    },
    "Silica_gel": {
      "moles": 1.3947664638784376,
      "mass_kg": 0.08379756914981654
    },
    "Ettringite": {
      "moles": 0.002562975,
      "mass_kg": 0.0032165336249999994
    },
    "Hydrotalcite": {
      "moles": 0.020506445999999998,
      "mass_kg": 0.009084355577999999
    }
  },
  "pH": 9.7400625,
  "pe": 4.0,
  "Eh": 0.24,
  "system_mass_kg": 0.153658336392075,
  "input_composition": {
    "Ca": 0.34011919,
    "Si": 1.73116109,
    "Al": 0.62412504,
    "Fe": 0.13813669,
    "Mg": 0.06835482,
    "K": 0.0833666,
    "Na": 0.06076591,
    "S": 0.01537785,
    "O": 12.14605597,
    "H": 13.9881256,
    "C": 0.00980229
  },
  "execution_time": 1.1444091796875e-05,
  "mix_id": "MIX_3489",
  "input_file": "/teamspace/studios/this_studio/inputs/generated/MIX_3489.inp"
}